Metadata-Version: 1.0
Name: autorest
Version: 0.1.0
Summary: autoREST is a tool to create simple REST API for legacy applications
Home-page: https://github.com/grycap/autorest
Author: Carlos de Alfonso
Author-email: caralla@upv.es
License: UNKNOWN
Platform: UNKNOWN
